odd_collector/__init__.py
odd_collector/__main__.py
odd_collector/adapters/__init__.py
odd_collector/adapters/airbyte/__init__.py
odd_collector/adapters/airbyte/adapter.py
odd_collector/adapters/airbyte/api.py
odd_collector/adapters/airbyte/logger.py
odd_collector/adapters/airbyte/mappers/__init__.py
odd_collector/adapters/airbyte/mappers/connections.py
odd_collector/adapters/airbyte/mappers/datasets.py
odd_collector/adapters/cassandra/__init__.py
odd_collector/adapters/cassandra/adapter.py
odd_collector/adapters/cassandra/mappers/__init__.py
odd_collector/adapters/cassandra/mappers/columns.py
odd_collector/adapters/cassandra/mappers/keyspaces.py
odd_collector/adapters/cassandra/mappers/metadata.py
odd_collector/adapters/cassandra/mappers/models.py
odd_collector/adapters/cassandra/mappers/tables.py
odd_collector/adapters/cassandra/mappers/types.py
odd_collector/adapters/cassandra/mappers/views.py
odd_collector/adapters/cassandra/repository.py
odd_collector/adapters/clickhouse/__init__.py
odd_collector/adapters/clickhouse/adapter.py
odd_collector/adapters/clickhouse/domain/__init__.py
odd_collector/adapters/clickhouse/domain/column.py
odd_collector/adapters/clickhouse/domain/integration_engine.py
odd_collector/adapters/clickhouse/domain/records.py
odd_collector/adapters/clickhouse/domain/table.py
odd_collector/adapters/clickhouse/logger.py
odd_collector/adapters/clickhouse/mappers/__init__.py
odd_collector/adapters/clickhouse/mappers/columns.py
odd_collector/adapters/clickhouse/mappers/integrated_engines/__init__.py
odd_collector/adapters/clickhouse/mappers/integrated_engines/engine_parsers.py
odd_collector/adapters/clickhouse/mappers/metadata.py
odd_collector/adapters/clickhouse/mappers/tables.py
odd_collector/adapters/clickhouse/mappers/transformer.py
odd_collector/adapters/clickhouse/mappers/types.py
odd_collector/adapters/clickhouse/repository.py
odd_collector/adapters/cubejs/__init__.py
odd_collector/adapters/cubejs/adapter.py
odd_collector-0.1.18.dist-info/METADATA
odd_collector-0.1.18.dist-info/WHEEL
odd_collector-0.1.18.dist-info/LICENSE
odd_collector-0.1.18.dist-info/RECORD
